{"kind":"symbol","variants":[{"traits":[{"interfaceLanguage":"swift"}],"paths":["\/documentation\/pacemakerradio\/swift\/string"]}],"schemaVersion":{"major":0,"minor":3,"patch":0},"primaryContentSections":[{"declarations":[{"tokens":[{"text":"extension","kind":"keyword"},{"text":" ","kind":"text"},{"kind":"typeIdentifier","text":"String","preciseIdentifier":"s:SS"}],"platforms":["iOS"],"languages":["swift"]}],"kind":"declarations"}],"topicSections":[{"generated":true,"identifiers":["doc:\/\/org.cocoapods.PacemakerRadio\/documentation\/PacemakerRadio\/Swift\/String\/A-5oh0s","doc:\/\/org.cocoapods.PacemakerRadio\/documentation\/PacemakerRadio\/Swift\/String\/B-4w7mw","doc:\/\/org.cocoapods.PacemakerRadio\/documentation\/PacemakerRadio\/Swift\/String\/C-8oc4x","doc:\/\/org.cocoapods.PacemakerRadio\/documentation\/PacemakerRadio\/Swift\/String\/D-4xt39","doc:\/\/org.cocoapods.PacemakerRadio\/documentation\/PacemakerRadio\/Swift\/String\/E-6fo8j","doc:\/\/org.cocoapods.PacemakerRadio\/documentation\/PacemakerRadio\/Swift\/String\/F-89zw3","doc:\/\/org.cocoapods.PacemakerRadio\/documentation\/PacemakerRadio\/Swift\/String\/G-4gmr8","doc:\/\/org.cocoapods.PacemakerRadio\/documentation\/PacemakerRadio\/Swift\/String\/H-6ow9j","doc:\/\/org.cocoapods.PacemakerRadio\/documentation\/PacemakerRadio\/Swift\/String\/I-9vxw8","doc:\/\/org.cocoapods.PacemakerRadio\/documentation\/PacemakerRadio\/Swift\/String\/J-2pise","doc:\/\/org.cocoapods.PacemakerRadio\/documentation\/PacemakerRadio\/Swift\/String\/K-6bn8p","doc:\/\/org.cocoapods.PacemakerRadio\/documentation\/PacemakerRadio\/Swift\/String\/L-4rbao","doc:\/\/org.cocoapods.PacemakerRadio\/documentation\/PacemakerRadio\/Swift\/String\/M-9j41q","doc:\/\/org.cocoapods.PacemakerRadio\/documentation\/PacemakerRadio\/Swift\/String\/N-80qox","doc:\/\/org.cocoapods.PacemakerRadio\/documentation\/PacemakerRadio\/Swift\/String\/O-90rz0","doc:\/\/org.cocoapods.PacemakerRadio\/documentation\/PacemakerRadio\/Swift\/String\/P-7ykf2","doc:\/\/org.cocoapods.PacemakerRadio\/documentation\/PacemakerRadio\/Swift\/String\/Q-9in6a","doc:\/\/org.cocoapods.PacemakerRadio\/documentation\/PacemakerRadio\/Swift\/String\/R-8g6mn","doc:\/\/org.cocoapods.PacemakerRadio\/documentation\/PacemakerRadio\/Swift\/String\/S-8ydbs","doc:\/\/org.cocoapods.PacemakerRadio\/documentation\/PacemakerRadio\/Swift\/String\/T-5a1pq","doc:\/\/org.cocoapods.PacemakerRadio\/documentation\/PacemakerRadio\/Swift\/String\/U-3tyrw","doc:\/\/org.cocoapods.PacemakerRadio\/documentation\/PacemakerRadio\/Swift\/String\/V-18lpl","doc:\/\/org.cocoapods.PacemakerRadio\/documentation\/PacemakerRadio\/Swift\/String\/W-9er54","doc:\/\/org.cocoapods.PacemakerRadio\/documentation\/PacemakerRadio\/Swift\/String\/X-4xctw","doc:\/\/org.cocoapods.PacemakerRadio\/documentation\/PacemakerRadio\/Swift\/String\/Y-48a0k","doc:\/\/org.cocoapods.PacemakerRadio\/documentation\/PacemakerRadio\/Swift\/String\/Z-6joow","doc:\/\/org.cocoapods.PacemakerRadio\/documentation\/PacemakerRadio\/Swift\/String\/a-6upzr","doc:\/\/org.cocoapods.PacemakerRadio\/documentation\/PacemakerRadio\/Swift\/String\/ampersand","doc:\/\/org.cocoapods.PacemakerRadio\/documentation\/PacemakerRadio\/Swift\/String\/apostrophe","doc:\/\/org.cocoapods.PacemakerRadio\/documentation\/PacemakerRadio\/Swift\/String\/asterisk","doc:\/\/org.cocoapods.PacemakerRadio\/documentation\/PacemakerRadio\/Swift\/String\/at","doc:\/\/org.cocoapods.PacemakerRadio\/documentation\/PacemakerRadio\/Swift\/String\/b-8gfk0","doc:\/\/org.cocoapods.PacemakerRadio\/documentation\/PacemakerRadio\/Swift\/String\/back_slash","doc:\/\/org.cocoapods.PacemakerRadio\/documentation\/PacemakerRadio\/Swift\/String\/bar","doc:\/\/org.cocoapods.PacemakerRadio\/documentation\/PacemakerRadio\/Swift\/String\/bracket_left","doc:\/\/org.cocoapods.PacemakerRadio\/documentation\/PacemakerRadio\/Swift\/String\/bracket_right","doc:\/\/org.cocoapods.PacemakerRadio\/documentation\/PacemakerRadio\/Swift\/String\/c-3cwyk","doc:\/\/org.cocoapods.PacemakerRadio\/documentation\/PacemakerRadio\/Swift\/String\/caret","doc:\/\/org.cocoapods.PacemakerRadio\/documentation\/PacemakerRadio\/Swift\/String\/colon","doc:\/\/org.cocoapods.PacemakerRadio\/documentation\/PacemakerRadio\/Swift\/String\/comma","doc:\/\/org.cocoapods.PacemakerRadio\/documentation\/PacemakerRadio\/Swift\/String\/curly_left","doc:\/\/org.cocoapods.PacemakerRadio\/documentation\/PacemakerRadio\/Swift\/String\/curly_right","doc:\/\/org.cocoapods.PacemakerRadio\/documentation\/PacemakerRadio\/Swift\/String\/d-9lzaj","doc:\/\/org.cocoapods.PacemakerRadio\/documentation\/PacemakerRadio\/Swift\/String\/dash","doc:\/\/org.cocoapods.PacemakerRadio\/documentation\/PacemakerRadio\/Swift\/String\/dollar","doc:\/\/org.cocoapods.PacemakerRadio\/documentation\/PacemakerRadio\/Swift\/String\/dot","doc:\/\/org.cocoapods.PacemakerRadio\/documentation\/PacemakerRadio\/Swift\/String\/e-8s30o","doc:\/\/org.cocoapods.PacemakerRadio\/documentation\/PacemakerRadio\/Swift\/String\/equals","doc:\/\/org.cocoapods.PacemakerRadio\/documentation\/PacemakerRadio\/Swift\/String\/exclamation","doc:\/\/org.cocoapods.PacemakerRadio\/documentation\/PacemakerRadio\/Swift\/String\/f-6ipgh","doc:\/\/org.cocoapods.PacemakerRadio\/documentation\/PacemakerRadio\/Swift\/String\/forward_slash","doc:\/\/org.cocoapods.PacemakerRadio\/documentation\/PacemakerRadio\/Swift\/String\/g-6qu19","doc:\/\/org.cocoapods.PacemakerRadio\/documentation\/PacemakerRadio\/Swift\/String\/greater_than","doc:\/\/org.cocoapods.PacemakerRadio\/documentation\/PacemakerRadio\/Swift\/String\/h-4xlz5","doc:\/\/org.cocoapods.PacemakerRadio\/documentation\/PacemakerRadio\/Swift\/String\/i-4kim7","doc:\/\/org.cocoapods.PacemakerRadio\/documentation\/PacemakerRadio\/Swift\/String\/j-3xz8n","doc:\/\/org.cocoapods.PacemakerRadio\/documentation\/PacemakerRadio\/Swift\/String\/k-7k3w0","doc:\/\/org.cocoapods.PacemakerRadio\/documentation\/PacemakerRadio\/Swift\/String\/l-8bj6g","doc:\/\/org.cocoapods.PacemakerRadio\/documentation\/PacemakerRadio\/Swift\/String\/less_than","doc:\/\/org.cocoapods.PacemakerRadio\/documentation\/PacemakerRadio\/Swift\/String\/localized","doc:\/\/org.cocoapods.PacemakerRadio\/documentation\/PacemakerRadio\/Swift\/String\/m-47oxx","doc:\/\/org.cocoapods.PacemakerRadio\/documentation\/PacemakerRadio\/Swift\/String\/n-2pbju","doc:\/\/org.cocoapods.PacemakerRadio\/documentation\/PacemakerRadio\/Swift\/String\/o-77a36","doc:\/\/org.cocoapods.PacemakerRadio\/documentation\/PacemakerRadio\/Swift\/String\/p-2n52z","doc:\/\/org.cocoapods.PacemakerRadio\/documentation\/PacemakerRadio\/Swift\/String\/paren_left","doc:\/\/org.cocoapods.PacemakerRadio\/documentation\/PacemakerRadio\/Swift\/String\/paren_right","doc:\/\/org.cocoapods.PacemakerRadio\/documentation\/PacemakerRadio\/Swift\/String\/percent","doc:\/\/org.cocoapods.PacemakerRadio\/documentation\/PacemakerRadio\/Swift\/String\/plus","doc:\/\/org.cocoapods.PacemakerRadio\/documentation\/PacemakerRadio\/Swift\/String\/point","doc:\/\/org.cocoapods.PacemakerRadio\/documentation\/PacemakerRadio\/Swift\/String\/pound","doc:\/\/org.cocoapods.PacemakerRadio\/documentation\/PacemakerRadio\/Swift\/String\/q-6l6pi","doc:\/\/org.cocoapods.PacemakerRadio\/documentation\/PacemakerRadio\/Swift\/String\/question_mark","doc:\/\/org.cocoapods.PacemakerRadio\/documentation\/PacemakerRadio\/Swift\/String\/quotation","doc:\/\/org.cocoapods.PacemakerRadio\/documentation\/PacemakerRadio\/Swift\/String\/r-6moql","doc:\/\/org.cocoapods.PacemakerRadio\/documentation\/PacemakerRadio\/Swift\/String\/s-9l1x3","doc:\/\/org.cocoapods.PacemakerRadio\/documentation\/PacemakerRadio\/Swift\/String\/semicolon","doc:\/\/org.cocoapods.PacemakerRadio\/documentation\/PacemakerRadio\/Swift\/String\/space","doc:\/\/org.cocoapods.PacemakerRadio\/documentation\/PacemakerRadio\/Swift\/String\/t-12krl","doc:\/\/org.cocoapods.PacemakerRadio\/documentation\/PacemakerRadio\/Swift\/String\/u-645yd","doc:\/\/org.cocoapods.PacemakerRadio\/documentation\/PacemakerRadio\/Swift\/String\/underscore","doc:\/\/org.cocoapods.PacemakerRadio\/documentation\/PacemakerRadio\/Swift\/String\/v-3367","doc:\/\/org.cocoapods.PacemakerRadio\/documentation\/PacemakerRadio\/Swift\/String\/w-lels","doc:\/\/org.cocoapods.PacemakerRadio\/documentation\/PacemakerRadio\/Swift\/String\/x-8hkz0","doc:\/\/org.cocoapods.PacemakerRadio\/documentation\/PacemakerRadio\/Swift\/String\/y-8ynx6","doc:\/\/org.cocoapods.PacemakerRadio\/documentation\/PacemakerRadio\/Swift\/String\/z-8tvvf"],"anchor":"Instance-Properties","title":"Instance Properties"}],"hierarchy":{"paths":[["doc:\/\/org.cocoapods.PacemakerRadio\/documentation\/PacemakerRadio","doc:\/\/org.cocoapods.PacemakerRadio\/documentation\/PacemakerRadio\/Swift"]]},"identifier":{"url":"doc:\/\/org.cocoapods.PacemakerRadio\/documentation\/PacemakerRadio\/Swift\/String","interfaceLanguage":"swift"},"metadata":{"externalID":"s:e:s:SS14PacemakerRadioE1ASSvp","extendedModule":"Swift","role":"symbol","title":"String","fragments":[{"kind":"keyword","text":"extension"},{"kind":"text","text":" "},{"preciseIdentifier":"s:SS","text":"String","kind":"identifier"}],"navigatorTitle":[{"text":"String","kind":"identifier"}],"symbolKind":"extension","roleHeading":"Extended Structure","modules":[{"relatedModules":["Swift"],"name":"PacemakerRadio"}]},"sections":[],"references":{"doc://org.cocoapods.PacemakerRadio/documentation/PacemakerRadio/Swift/String/bracket_left":{"kind":"symbol","role":"symbol","abstract":[],"title":"bracket_left","type":"topic","url":"\/documentation\/pacemakerradio\/swift\/string\/bracket_left","fragments":[{"text":"var","kind":"keyword"},{"text":" ","kind":"text"},{"text":"bracket_left","kind":"identifier"},{"kind":"text","text":": "},{"preciseIdentifier":"s:SS","kind":"typeIdentifier","text":"String"}],"identifier":"doc:\/\/org.cocoapods.PacemakerRadio\/documentation\/PacemakerRadio\/Swift\/String\/bracket_left"},"doc://org.cocoapods.PacemakerRadio/documentation/PacemakerRadio/Swift/String/O-90rz0":{"kind":"symbol","url":"\/documentation\/pacemakerradio\/swift\/string\/o-90rz0","identifier":"doc:\/\/org.cocoapods.PacemakerRadio\/documentation\/PacemakerRadio\/Swift\/String\/O-90rz0","role":"symbol","title":"O","abstract":[],"fragments":[{"kind":"keyword","text":"var"},{"kind":"text","text":" "},{"kind":"identifier","text":"O"},{"kind":"text","text":": "},{"kind":"typeIdentifier","preciseIdentifier":"s:SS","text":"String"}],"type":"topic"},"doc://org.cocoapods.PacemakerRadio/documentation/PacemakerRadio/Swift/String":{"type":"topic","url":"\/documentation\/pacemakerradio\/swift\/string","identifier":"doc:\/\/org.cocoapods.PacemakerRadio\/documentation\/PacemakerRadio\/Swift\/String","abstract":[],"role":"symbol","fragments":[{"text":"extension","kind":"keyword"},{"text":" ","kind":"text"},{"text":"String","kind":"identifier","preciseIdentifier":"s:SS"}],"navigatorTitle":[{"text":"String","kind":"identifier"}],"kind":"symbol","title":"String"},"doc://org.cocoapods.PacemakerRadio/documentation/PacemakerRadio/Swift/String/less_than":{"kind":"symbol","role":"symbol","abstract":[],"title":"less_than","type":"topic","url":"\/documentation\/pacemakerradio\/swift\/string\/less_than","fragments":[{"kind":"keyword","text":"var"},{"kind":"text","text":" "},{"kind":"identifier","text":"less_than"},{"kind":"text","text":": "},{"preciseIdentifier":"s:SS","kind":"typeIdentifier","text":"String"}],"identifier":"doc:\/\/org.cocoapods.PacemakerRadio\/documentation\/PacemakerRadio\/Swift\/String\/less_than"},"doc://org.cocoapods.PacemakerRadio/documentation/PacemakerRadio/Swift/String/M-9j41q":{"title":"M","abstract":[],"kind":"symbol","fragments":[{"text":"var","kind":"keyword"},{"text":" ","kind":"text"},{"kind":"identifier","text":"M"},{"text":": ","kind":"text"},{"text":"String","kind":"typeIdentifier","preciseIdentifier":"s:SS"}],"url":"\/documentation\/pacemakerradio\/swift\/string\/m-9j41q","role":"symbol","type":"topic","identifier":"doc:\/\/org.cocoapods.PacemakerRadio\/documentation\/PacemakerRadio\/Swift\/String\/M-9j41q"},"doc://org.cocoapods.PacemakerRadio/documentation/PacemakerRadio/Swift/String/z-8tvvf":{"type":"topic","abstract":[],"kind":"symbol","url":"\/documentation\/pacemakerradio\/swift\/string\/z-8tvvf","title":"z","fragments":[{"kind":"keyword","text":"var"},{"text":" ","kind":"text"},{"kind":"identifier","text":"z"},{"text":": ","kind":"text"},{"preciseIdentifier":"s:SS","text":"String","kind":"typeIdentifier"}],"identifier":"doc:\/\/org.cocoapods.PacemakerRadio\/documentation\/PacemakerRadio\/Swift\/String\/z-8tvvf","role":"symbol"},"doc://org.cocoapods.PacemakerRadio/documentation/PacemakerRadio/Swift/String/percent":{"url":"\/documentation\/pacemakerradio\/swift\/string\/percent","type":"topic","identifier":"doc:\/\/org.cocoapods.PacemakerRadio\/documentation\/PacemakerRadio\/Swift\/String\/percent","abstract":[],"role":"symbol","kind":"symbol","title":"percent","fragments":[{"kind":"keyword","text":"var"},{"text":" ","kind":"text"},{"text":"percent","kind":"identifier"},{"text":": ","kind":"text"},{"text":"String","preciseIdentifier":"s:SS","kind":"typeIdentifier"}]},"doc://org.cocoapods.PacemakerRadio/documentation/PacemakerRadio/Swift/String/B-4w7mw":{"url":"\/documentation\/pacemakerradio\/swift\/string\/b-4w7mw","type":"topic","kind":"symbol","abstract":[],"role":"symbol","fragments":[{"text":"var","kind":"keyword"},{"kind":"text","text":" "},{"text":"B","kind":"identifier"},{"kind":"text","text":": "},{"text":"String","kind":"typeIdentifier","preciseIdentifier":"s:SS"}],"title":"B","identifier":"doc:\/\/org.cocoapods.PacemakerRadio\/documentation\/PacemakerRadio\/Swift\/String\/B-4w7mw"},"doc://org.cocoapods.PacemakerRadio/documentation/PacemakerRadio/Swift/String/x-8hkz0":{"abstract":[],"identifier":"doc:\/\/org.cocoapods.PacemakerRadio\/documentation\/PacemakerRadio\/Swift\/String\/x-8hkz0","fragments":[{"text":"var","kind":"keyword"},{"text":" ","kind":"text"},{"text":"x","kind":"identifier"},{"text":": ","kind":"text"},{"kind":"typeIdentifier","preciseIdentifier":"s:SS","text":"String"}],"kind":"symbol","url":"\/documentation\/pacemakerradio\/swift\/string\/x-8hkz0","type":"topic","title":"x","role":"symbol"},"doc://org.cocoapods.PacemakerRadio/documentation/PacemakerRadio/Swift/String/y-8ynx6":{"fragments":[{"kind":"keyword","text":"var"},{"text":" ","kind":"text"},{"kind":"identifier","text":"y"},{"kind":"text","text":": "},{"kind":"typeIdentifier","preciseIdentifier":"s:SS","text":"String"}],"identifier":"doc:\/\/org.cocoapods.PacemakerRadio\/documentation\/PacemakerRadio\/Swift\/String\/y-8ynx6","kind":"symbol","type":"topic","title":"y","url":"\/documentation\/pacemakerradio\/swift\/string\/y-8ynx6","abstract":[],"role":"symbol"},"doc://org.cocoapods.PacemakerRadio/documentation/PacemakerRadio/Swift/String/T-5a1pq":{"abstract":[],"fragments":[{"text":"var","kind":"keyword"},{"text":" ","kind":"text"},{"text":"T","kind":"identifier"},{"text":": ","kind":"text"},{"kind":"typeIdentifier","preciseIdentifier":"s:SS","text":"String"}],"title":"T","identifier":"doc:\/\/org.cocoapods.PacemakerRadio\/documentation\/PacemakerRadio\/Swift\/String\/T-5a1pq","url":"\/documentation\/pacemakerradio\/swift\/string\/t-5a1pq","role":"symbol","kind":"symbol","type":"topic"},"doc://org.cocoapods.PacemakerRadio/documentation/PacemakerRadio/Swift/String/o-77a36":{"role":"symbol","url":"\/documentation\/pacemakerradio\/swift\/string\/o-77a36","fragments":[{"kind":"keyword","text":"var"},{"text":" ","kind":"text"},{"text":"o","kind":"identifier"},{"text":": ","kind":"text"},{"text":"String","kind":"typeIdentifier","preciseIdentifier":"s:SS"}],"kind":"symbol","type":"topic","identifier":"doc:\/\/org.cocoapods.PacemakerRadio\/documentation\/PacemakerRadio\/Swift\/String\/o-77a36","abstract":[],"title":"o"},"doc://org.cocoapods.PacemakerRadio/documentation/PacemakerRadio/Swift/String/N-80qox":{"abstract":[],"identifier":"doc:\/\/org.cocoapods.PacemakerRadio\/documentation\/PacemakerRadio\/Swift\/String\/N-80qox","fragments":[{"text":"var","kind":"keyword"},{"text":" ","kind":"text"},{"text":"N","kind":"identifier"},{"text":": ","kind":"text"},{"kind":"typeIdentifier","preciseIdentifier":"s:SS","text":"String"}],"kind":"symbol","url":"\/documentation\/pacemakerradio\/swift\/string\/n-80qox","type":"topic","title":"N","role":"symbol"},"doc://org.cocoapods.PacemakerRadio/documentation/PacemakerRadio/Swift/String/r-6moql":{"role":"symbol","url":"\/documentation\/pacemakerradio\/swift\/string\/r-6moql","fragments":[{"kind":"keyword","text":"var"},{"text":" ","kind":"text"},{"text":"r","kind":"identifier"},{"text":": ","kind":"text"},{"text":"String","kind":"typeIdentifier","preciseIdentifier":"s:SS"}],"kind":"symbol","type":"topic","identifier":"doc:\/\/org.cocoapods.PacemakerRadio\/documentation\/PacemakerRadio\/Swift\/String\/r-6moql","abstract":[],"title":"r"},"doc://org.cocoapods.PacemakerRadio/documentation/PacemakerRadio/Swift/String/equals":{"role":"symbol","url":"\/documentation\/pacemakerradio\/swift\/string\/equals","abstract":[],"identifier":"doc:\/\/org.cocoapods.PacemakerRadio\/documentation\/PacemakerRadio\/Swift\/String\/equals","fragments":[{"text":"var","kind":"keyword"},{"kind":"text","text":" "},{"text":"equals","kind":"identifier"},{"kind":"text","text":": "},{"text":"String","kind":"typeIdentifier","preciseIdentifier":"s:SS"}],"title":"equals","kind":"symbol","type":"topic"},"doc://org.cocoapods.PacemakerRadio/documentation/PacemakerRadio/Swift/String/w-lels":{"type":"topic","kind":"symbol","title":"w","role":"symbol","identifier":"doc:\/\/org.cocoapods.PacemakerRadio\/documentation\/PacemakerRadio\/Swift\/String\/w-lels","url":"\/documentation\/pacemakerradio\/swift\/string\/w-lels","abstract":[],"fragments":[{"text":"var","kind":"keyword"},{"kind":"text","text":" "},{"text":"w","kind":"identifier"},{"kind":"text","text":": "},{"kind":"typeIdentifier","text":"String","preciseIdentifier":"s:SS"}]},"doc://org.cocoapods.PacemakerRadio/documentation/PacemakerRadio/Swift/String/exclamation":{"type":"topic","abstract":[],"url":"\/documentation\/pacemakerradio\/swift\/string\/exclamation","fragments":[{"kind":"keyword","text":"var"},{"kind":"text","text":" "},{"kind":"identifier","text":"exclamation"},{"kind":"text","text":": "},{"preciseIdentifier":"s:SS","kind":"typeIdentifier","text":"String"}],"identifier":"doc:\/\/org.cocoapods.PacemakerRadio\/documentation\/PacemakerRadio\/Swift\/String\/exclamation","kind":"symbol","role":"symbol","title":"exclamation"},"doc://org.cocoapods.PacemakerRadio/documentation/PacemakerRadio/Swift/String/q-6l6pi":{"abstract":[],"role":"symbol","kind":"symbol","identifier":"doc:\/\/org.cocoapods.PacemakerRadio\/documentation\/PacemakerRadio\/Swift\/String\/q-6l6pi","fragments":[{"kind":"keyword","text":"var"},{"text":" ","kind":"text"},{"text":"q","kind":"identifier"},{"text":": ","kind":"text"},{"kind":"typeIdentifier","preciseIdentifier":"s:SS","text":"String"}],"title":"q","type":"topic","url":"\/documentation\/pacemakerradio\/swift\/string\/q-6l6pi"},"doc://org.cocoapods.PacemakerRadio/documentation/PacemakerRadio/Swift/String/paren_right":{"type":"topic","kind":"symbol","title":"paren_right","role":"symbol","identifier":"doc:\/\/org.cocoapods.PacemakerRadio\/documentation\/PacemakerRadio\/Swift\/String\/paren_right","url":"\/documentation\/pacemakerradio\/swift\/string\/paren_right","abstract":[],"fragments":[{"text":"var","kind":"keyword"},{"kind":"text","text":" "},{"kind":"identifier","text":"paren_right"},{"text":": ","kind":"text"},{"kind":"typeIdentifier","preciseIdentifier":"s:SS","text":"String"}]},"doc://org.cocoapods.PacemakerRadio/documentation/PacemakerRadio/Swift/String/u-645yd":{"role":"symbol","kind":"symbol","url":"\/documentation\/pacemakerradio\/swift\/string\/u-645yd","identifier":"doc:\/\/org.cocoapods.PacemakerRadio\/documentation\/PacemakerRadio\/Swift\/String\/u-645yd","title":"u","type":"topic","fragments":[{"kind":"keyword","text":"var"},{"text":" ","kind":"text"},{"kind":"identifier","text":"u"},{"kind":"text","text":": "},{"preciseIdentifier":"s:SS","text":"String","kind":"typeIdentifier"}],"abstract":[]},"doc://org.cocoapods.PacemakerRadio/documentation/PacemakerRadio/Swift/String/p-2n52z":{"type":"topic","kind":"symbol","title":"p","role":"symbol","identifier":"doc:\/\/org.cocoapods.PacemakerRadio\/documentation\/PacemakerRadio\/Swift\/String\/p-2n52z","abstract":[],"url":"\/documentation\/pacemakerradio\/swift\/string\/p-2n52z","fragments":[{"text":"var","kind":"keyword"},{"text":" ","kind":"text"},{"text":"p","kind":"identifier"},{"text":": ","kind":"text"},{"preciseIdentifier":"s:SS","text":"String","kind":"typeIdentifier"}]},"doc://org.cocoapods.PacemakerRadio/documentation/PacemakerRadio/Swift/String/m-47oxx":{"type":"topic","kind":"symbol","title":"m","role":"symbol","identifier":"doc:\/\/org.cocoapods.PacemakerRadio\/documentation\/PacemakerRadio\/Swift\/String\/m-47oxx","url":"\/documentation\/pacemakerradio\/swift\/string\/m-47oxx","abstract":[],"fragments":[{"text":"var","kind":"keyword"},{"kind":"text","text":" "},{"kind":"identifier","text":"m"},{"text":": ","kind":"text"},{"kind":"typeIdentifier","preciseIdentifier":"s:SS","text":"String"}]},"doc://org.cocoapods.PacemakerRadio/documentation/PacemakerRadio/Swift/String/pound":{"fragments":[{"text":"var","kind":"keyword"},{"kind":"text","text":" "},{"kind":"identifier","text":"pound"},{"kind":"text","text":": "},{"kind":"typeIdentifier","preciseIdentifier":"s:SS","text":"String"}],"url":"\/documentation\/pacemakerradio\/swift\/string\/pound","identifier":"doc:\/\/org.cocoapods.PacemakerRadio\/documentation\/PacemakerRadio\/Swift\/String\/pound","title":"pound","role":"symbol","abstract":[],"kind":"symbol","type":"topic"},"doc://org.cocoapods.PacemakerRadio/documentation/PacemakerRadio/Swift/String/t-12krl":{"role":"symbol","kind":"symbol","url":"\/documentation\/pacemakerradio\/swift\/string\/t-12krl","identifier":"doc:\/\/org.cocoapods.PacemakerRadio\/documentation\/PacemakerRadio\/Swift\/String\/t-12krl","title":"t","type":"topic","fragments":[{"kind":"keyword","text":"var"},{"text":" ","kind":"text"},{"kind":"identifier","text":"t"},{"kind":"text","text":": "},{"preciseIdentifier":"s:SS","text":"String","kind":"typeIdentifier"}],"abstract":[]},"doc://org.cocoapods.PacemakerRadio/documentation/PacemakerRadio/Swift/String/point":{"title":"point","type":"topic","role":"symbol","url":"\/documentation\/pacemakerradio\/swift\/string\/point","identifier":"doc:\/\/org.cocoapods.PacemakerRadio\/documentation\/PacemakerRadio\/Swift\/String\/point","fragments":[{"kind":"keyword","text":"var"},{"text":" ","kind":"text"},{"kind":"identifier","text":"point"},{"kind":"text","text":": "},{"kind":"typeIdentifier","preciseIdentifier":"s:SS","text":"String"}],"abstract":[],"kind":"symbol"},"doc://org.cocoapods.PacemakerRadio/documentation/PacemakerRadio/Swift/String/Y-48a0k":{"type":"topic","kind":"symbol","title":"Y","role":"symbol","identifier":"doc:\/\/org.cocoapods.PacemakerRadio\/documentation\/PacemakerRadio\/Swift\/String\/Y-48a0k","url":"\/documentation\/pacemakerradio\/swift\/string\/y-48a0k","abstract":[],"fragments":[{"text":"var","kind":"keyword"},{"text":" ","kind":"text"},{"text":"Y","kind":"identifier"},{"text":": ","kind":"text"},{"preciseIdentifier":"s:SS","text":"String","kind":"typeIdentifier"}]},"doc://org.cocoapods.PacemakerRadio/documentation/PacemakerRadio/Swift/String/d-9lzaj":{"role":"symbol","kind":"symbol","url":"\/documentation\/pacemakerradio\/swift\/string\/d-9lzaj","identifier":"doc:\/\/org.cocoapods.PacemakerRadio\/documentation\/PacemakerRadio\/Swift\/String\/d-9lzaj","title":"d","type":"topic","fragments":[{"kind":"keyword","text":"var"},{"text":" ","kind":"text"},{"kind":"identifier","text":"d"},{"kind":"text","text":": "},{"kind":"typeIdentifier","preciseIdentifier":"s:SS","text":"String"}],"abstract":[]},"doc://org.cocoapods.PacemakerRadio/documentation/PacemakerRadio/Swift/String/k-7k3w0":{"type":"topic","kind":"symbol","title":"k","role":"symbol","identifier":"doc:\/\/org.cocoapods.PacemakerRadio\/documentation\/PacemakerRadio\/Swift\/String\/k-7k3w0","url":"\/documentation\/pacemakerradio\/swift\/string\/k-7k3w0","abstract":[],"fragments":[{"text":"var","kind":"keyword"},{"kind":"text","text":" "},{"kind":"identifier","text":"k"},{"text":": ","kind":"text"},{"kind":"typeIdentifier","preciseIdentifier":"s:SS","text":"String"}]},"doc://org.cocoapods.PacemakerRadio/documentation/PacemakerRadio/Swift/String/U-3tyrw":{"role":"symbol","kind":"symbol","url":"\/documentation\/pacemakerradio\/swift\/string\/u-3tyrw","identifier":"doc:\/\/org.cocoapods.PacemakerRadio\/documentation\/PacemakerRadio\/Swift\/String\/U-3tyrw","title":"U","type":"topic","fragments":[{"text":"var","kind":"keyword"},{"kind":"text","text":" "},{"kind":"identifier","text":"U"},{"kind":"text","text":": "},{"preciseIdentifier":"s:SS","kind":"typeIdentifier","text":"String"}],"abstract":[]},"doc://org.cocoapods.PacemakerRadio/documentation/PacemakerRadio/Swift/String/quotation":{"url":"\/documentation\/pacemakerradio\/swift\/string\/quotation","role":"symbol","kind":"symbol","abstract":[],"type":"topic","title":"quotation","fragments":[{"text":"var","kind":"keyword"},{"kind":"text","text":" "},{"text":"quotation","kind":"identifier"},{"kind":"text","text":": "},{"text":"String","preciseIdentifier":"s:SS","kind":"typeIdentifier"}],"identifier":"doc:\/\/org.cocoapods.PacemakerRadio\/documentation\/PacemakerRadio\/Swift\/String\/quotation"},"doc://org.cocoapods.PacemakerRadio/documentation/PacemakerRadio/Swift/String/F-89zw3":{"role":"symbol","kind":"symbol","url":"\/documentation\/pacemakerradio\/swift\/string\/f-89zw3","identifier":"doc:\/\/org.cocoapods.PacemakerRadio\/documentation\/PacemakerRadio\/Swift\/String\/F-89zw3","title":"F","type":"topic","fragments":[{"kind":"keyword","text":"var"},{"text":" ","kind":"text"},{"kind":"identifier","text":"F"},{"kind":"text","text":": "},{"preciseIdentifier":"s:SS","text":"String","kind":"typeIdentifier"}],"abstract":[]},"doc://org.cocoapods.PacemakerRadio/documentation/PacemakerRadio/Swift/String/R-8g6mn":{"type":"topic","kind":"symbol","title":"R","role":"symbol","identifier":"doc:\/\/org.cocoapods.PacemakerRadio\/documentation\/PacemakerRadio\/Swift\/String\/R-8g6mn","url":"\/documentation\/pacemakerradio\/swift\/string\/r-8g6mn","abstract":[],"fragments":[{"text":"var","kind":"keyword"},{"kind":"text","text":" "},{"kind":"identifier","text":"R"},{"text":": ","kind":"text"},{"kind":"typeIdentifier","preciseIdentifier":"s:SS","text":"String"}]},"doc://org.cocoapods.PacemakerRadio/documentation/PacemakerRadio/Swift/String/n-2pbju":{"role":"symbol","kind":"symbol","url":"\/documentation\/pacemakerradio\/swift\/string\/n-2pbju","identifier":"doc:\/\/org.cocoapods.PacemakerRadio\/documentation\/PacemakerRadio\/Swift\/String\/n-2pbju","title":"n","type":"topic","fragments":[{"text":"var","kind":"keyword"},{"kind":"text","text":" "},{"text":"n","kind":"identifier"},{"kind":"text","text":": "},{"kind":"typeIdentifier","preciseIdentifier":"s:SS","text":"String"}],"abstract":[]},"doc://org.cocoapods.PacemakerRadio/documentation/PacemakerRadio/Swift/String/Q-9in6a":{"role":"symbol","kind":"symbol","url":"\/documentation\/pacemakerradio\/swift\/string\/q-9in6a","identifier":"doc:\/\/org.cocoapods.PacemakerRadio\/documentation\/PacemakerRadio\/Swift\/String\/Q-9in6a","title":"Q","type":"topic","fragments":[{"kind":"keyword","text":"var"},{"text":" ","kind":"text"},{"kind":"identifier","text":"Q"},{"kind":"text","text":": "},{"preciseIdentifier":"s:SS","text":"String","kind":"typeIdentifier"}],"abstract":[]},"doc://org.cocoapods.PacemakerRadio/documentation/PacemakerRadio/Swift":{"type":"topic","kind":"symbol","title":"Swift","role":"collection","identifier":"doc:\/\/org.cocoapods.PacemakerRadio\/documentation\/PacemakerRadio\/Swift","abstract":[],"url":"\/documentation\/pacemakerradio\/swift"},"doc://org.cocoapods.PacemakerRadio/documentation/PacemakerRadio/Swift/String/S-8ydbs":{"fragments":[{"kind":"keyword","text":"var"},{"kind":"text","text":" "},{"text":"S","kind":"identifier"},{"kind":"text","text":": "},{"kind":"typeIdentifier","text":"String","preciseIdentifier":"s:SS"}],"type":"topic","abstract":[],"kind":"symbol","role":"symbol","identifier":"doc:\/\/org.cocoapods.PacemakerRadio\/documentation\/PacemakerRadio\/Swift\/String\/S-8ydbs","url":"\/documentation\/pacemakerradio\/swift\/string\/s-8ydbs","title":"S"},"doc://org.cocoapods.PacemakerRadio/documentation/PacemakerRadio/Swift/String/dollar":{"type":"topic","kind":"symbol","title":"dollar","role":"symbol","identifier":"doc:\/\/org.cocoapods.PacemakerRadio\/documentation\/PacemakerRadio\/Swift\/String\/dollar","url":"\/documentation\/pacemakerradio\/swift\/string\/dollar","abstract":[],"fragments":[{"text":"var","kind":"keyword"},{"kind":"text","text":" "},{"kind":"identifier","text":"dollar"},{"text":": ","kind":"text"},{"kind":"typeIdentifier","preciseIdentifier":"s:SS","text":"String"}]},"doc://org.cocoapods.PacemakerRadio/documentation/PacemakerRadio/Swift/String/P-7ykf2":{"role":"symbol","kind":"symbol","url":"\/documentation\/pacemakerradio\/swift\/string\/p-7ykf2","identifier":"doc:\/\/org.cocoapods.PacemakerRadio\/documentation\/PacemakerRadio\/Swift\/String\/P-7ykf2","title":"P","type":"topic","fragments":[{"kind":"keyword","text":"var"},{"text":" ","kind":"text"},{"kind":"identifier","text":"P"},{"kind":"text","text":": "},{"preciseIdentifier":"s:SS","text":"String","kind":"typeIdentifier"}],"abstract":[]},"doc://org.cocoapods.PacemakerRadio/documentation/PacemakerRadio/Swift/String/question_mark":{"fragments":[{"text":"var","kind":"keyword"},{"text":" ","kind":"text"},{"text":"question_mark","kind":"identifier"},{"text":": ","kind":"text"},{"kind":"typeIdentifier","text":"String","preciseIdentifier":"s:SS"}],"abstract":[],"title":"question_mark","identifier":"doc:\/\/org.cocoapods.PacemakerRadio\/documentation\/PacemakerRadio\/Swift\/String\/question_mark","url":"\/documentation\/pacemakerradio\/swift\/string\/question_mark","type":"topic","kind":"symbol","role":"symbol"},"doc://org.cocoapods.PacemakerRadio/documentation/PacemakerRadio/Swift/String/K-6bn8p":{"title":"K","kind":"symbol","role":"symbol","fragments":[{"text":"var","kind":"keyword"},{"kind":"text","text":" "},{"text":"K","kind":"identifier"},{"kind":"text","text":": "},{"preciseIdentifier":"s:SS","kind":"typeIdentifier","text":"String"}],"url":"\/documentation\/pacemakerradio\/swift\/string\/k-6bn8p","type":"topic","abstract":[],"identifier":"doc:\/\/org.cocoapods.PacemakerRadio\/documentation\/PacemakerRadio\/Swift\/String\/K-6bn8p"},"doc://org.cocoapods.PacemakerRadio/documentation/PacemakerRadio/Swift/String/f-6ipgh":{"url":"\/documentation\/pacemakerradio\/swift\/string\/f-6ipgh","title":"f","type":"topic","kind":"symbol","fragments":[{"text":"var","kind":"keyword"},{"text":" ","kind":"text"},{"kind":"identifier","text":"f"},{"kind":"text","text":": "},{"preciseIdentifier":"s:SS","kind":"typeIdentifier","text":"String"}],"identifier":"doc:\/\/org.cocoapods.PacemakerRadio\/documentation\/PacemakerRadio\/Swift\/String\/f-6ipgh","abstract":[],"role":"symbol"},"doc://org.cocoapods.PacemakerRadio/documentation/PacemakerRadio/Swift/String/h-4xlz5":{"type":"topic","kind":"symbol","title":"h","role":"symbol","identifier":"doc:\/\/org.cocoapods.PacemakerRadio\/documentation\/PacemakerRadio\/Swift\/String\/h-4xlz5","url":"\/documentation\/pacemakerradio\/swift\/string\/h-4xlz5","abstract":[],"fragments":[{"text":"var","kind":"keyword"},{"kind":"text","text":" "},{"kind":"identifier","text":"h"},{"text":": ","kind":"text"},{"kind":"typeIdentifier","preciseIdentifier":"s:SS","text":"String"}]},"doc://org.cocoapods.PacemakerRadio/documentation/PacemakerRadio/Swift/String/Z-6joow":{"role":"symbol","kind":"symbol","url":"\/documentation\/pacemakerradio\/swift\/string\/z-6joow","identifier":"doc:\/\/org.cocoapods.PacemakerRadio\/documentation\/PacemakerRadio\/Swift\/String\/Z-6joow","title":"Z","type":"topic","fragments":[{"kind":"keyword","text":"var"},{"text":" ","kind":"text"},{"kind":"identifier","text":"Z"},{"kind":"text","text":": "},{"preciseIdentifier":"s:SS","text":"String","kind":"typeIdentifier"}],"abstract":[]},"doc://org.cocoapods.PacemakerRadio/documentation/PacemakerRadio/Swift/String/underscore":{"type":"topic","kind":"symbol","title":"underscore","role":"symbol","identifier":"doc:\/\/org.cocoapods.PacemakerRadio\/documentation\/PacemakerRadio\/Swift\/String\/underscore","url":"\/documentation\/pacemakerradio\/swift\/string\/underscore","abstract":[],"fragments":[{"text":"var","kind":"keyword"},{"kind":"text","text":" "},{"kind":"identifier","text":"underscore"},{"text":": ","kind":"text"},{"kind":"typeIdentifier","preciseIdentifier":"s:SS","text":"String"}]},"doc://org.cocoapods.PacemakerRadio/documentation/PacemakerRadio/Swift/String/curly_right":{"role":"symbol","kind":"symbol","url":"\/documentation\/pacemakerradio\/swift\/string\/curly_right","identifier":"doc:\/\/org.cocoapods.PacemakerRadio\/documentation\/PacemakerRadio\/Swift\/String\/curly_right","title":"curly_right","type":"topic","fragments":[{"kind":"keyword","text":"var"},{"text":" ","kind":"text"},{"kind":"identifier","text":"curly_right"},{"kind":"text","text":": "},{"preciseIdentifier":"s:SS","text":"String","kind":"typeIdentifier"}],"abstract":[]},"doc://org.cocoapods.PacemakerRadio/documentation/PacemakerRadio/Swift/String/localized":{"type":"topic","kind":"symbol","title":"localized","role":"symbol","identifier":"doc:\/\/org.cocoapods.PacemakerRadio\/documentation\/PacemakerRadio\/Swift\/String\/localized","url":"\/documentation\/pacemakerradio\/swift\/string\/localized","abstract":[],"fragments":[{"text":"var","kind":"keyword"},{"kind":"text","text":" "},{"kind":"identifier","text":"localized"},{"text":": ","kind":"text"},{"kind":"typeIdentifier","preciseIdentifier":"s:SS","text":"String"}]},"doc://org.cocoapods.PacemakerRadio/documentation/PacemakerRadio/Swift/String/e-8s30o":{"role":"symbol","kind":"symbol","url":"\/documentation\/pacemakerradio\/swift\/string\/e-8s30o","identifier":"doc:\/\/org.cocoapods.PacemakerRadio\/documentation\/PacemakerRadio\/Swift\/String\/e-8s30o","title":"e","type":"topic","fragments":[{"kind":"keyword","text":"var"},{"text":" ","kind":"text"},{"kind":"identifier","text":"e"},{"kind":"text","text":": "},{"preciseIdentifier":"s:SS","text":"String","kind":"typeIdentifier"}],"abstract":[]},"doc://org.cocoapods.PacemakerRadio/documentation/PacemakerRadio/Swift/String/greater_than":{"type":"topic","kind":"symbol","title":"greater_than","role":"symbol","identifier":"doc:\/\/org.cocoapods.PacemakerRadio\/documentation\/PacemakerRadio\/Swift\/String\/greater_than","url":"\/documentation\/pacemakerradio\/swift\/string\/greater_than","abstract":[],"fragments":[{"text":"var","kind":"keyword"},{"kind":"text","text":" "},{"kind":"identifier","text":"greater_than"},{"text":": ","kind":"text"},{"kind":"typeIdentifier","preciseIdentifier":"s:SS","text":"String"}]},"doc://org.cocoapods.PacemakerRadio/documentation/PacemakerRadio/Swift/String/C-8oc4x":{"role":"symbol","kind":"symbol","url":"\/documentation\/pacemakerradio\/swift\/string\/c-8oc4x","identifier":"doc:\/\/org.cocoapods.PacemakerRadio\/documentation\/PacemakerRadio\/Swift\/String\/C-8oc4x","title":"C","type":"topic","fragments":[{"kind":"keyword","text":"var"},{"text":" ","kind":"text"},{"kind":"identifier","text":"C"},{"kind":"text","text":": "},{"preciseIdentifier":"s:SS","text":"String","kind":"typeIdentifier"}],"abstract":[]},"doc://org.cocoapods.PacemakerRadio/documentation/PacemakerRadio/Swift/String/D-4xt39":{"title":"D","abstract":[],"fragments":[{"text":"var","kind":"keyword"},{"text":" ","kind":"text"},{"kind":"identifier","text":"D"},{"text":": ","kind":"text"},{"text":"String","preciseIdentifier":"s:SS","kind":"typeIdentifier"}],"identifier":"doc:\/\/org.cocoapods.PacemakerRadio\/documentation\/PacemakerRadio\/Swift\/String\/D-4xt39","kind":"symbol","url":"\/documentation\/pacemakerradio\/swift\/string\/d-4xt39","type":"topic","role":"symbol"},"doc://org.cocoapods.PacemakerRadio/documentation/PacemakerRadio/Swift/String/l-8bj6g":{"type":"topic","kind":"symbol","title":"l","role":"symbol","identifier":"doc:\/\/org.cocoapods.PacemakerRadio\/documentation\/PacemakerRadio\/Swift\/String\/l-8bj6g","url":"\/documentation\/pacemakerradio\/swift\/string\/l-8bj6g","abstract":[],"fragments":[{"text":"var","kind":"keyword"},{"kind":"text","text":" "},{"kind":"identifier","text":"l"},{"text":": ","kind":"text"},{"kind":"typeIdentifier","preciseIdentifier":"s:SS","text":"String"}]},"doc://org.cocoapods.PacemakerRadio/documentation/PacemakerRadio/Swift/String/i-4kim7":{"kind":"symbol","url":"\/documentation\/pacemakerradio\/swift\/string\/i-4kim7","role":"symbol","title":"i","abstract":[],"identifier":"doc:\/\/org.cocoapods.PacemakerRadio\/documentation\/PacemakerRadio\/Swift\/String\/i-4kim7","type":"topic","fragments":[{"text":"var","kind":"keyword"},{"text":" ","kind":"text"},{"kind":"identifier","text":"i"},{"text":": ","kind":"text"},{"text":"String","preciseIdentifier":"s:SS","kind":"typeIdentifier"}]},"doc://org.cocoapods.PacemakerRadio/documentation/PacemakerRadio/Swift/String/b-8gfk0":{"role":"symbol","kind":"symbol","url":"\/documentation\/pacemakerradio\/swift\/string\/b-8gfk0","identifier":"doc:\/\/org.cocoapods.PacemakerRadio\/documentation\/PacemakerRadio\/Swift\/String\/b-8gfk0","title":"b","type":"topic","fragments":[{"kind":"keyword","text":"var"},{"text":" ","kind":"text"},{"kind":"identifier","text":"b"},{"kind":"text","text":": "},{"preciseIdentifier":"s:SS","text":"String","kind":"typeIdentifier"}],"abstract":[]},"doc://org.cocoapods.PacemakerRadio/documentation/PacemakerRadio/Swift/String/back_slash":{"identifier":"doc:\/\/org.cocoapods.PacemakerRadio\/documentation\/PacemakerRadio\/Swift\/String\/back_slash","abstract":[],"title":"back_slash","type":"topic","url":"\/documentation\/pacemakerradio\/swift\/string\/back_slash","role":"symbol","fragments":[{"text":"var","kind":"keyword"},{"text":" ","kind":"text"},{"text":"back_slash","kind":"identifier"},{"kind":"text","text":": "},{"text":"String","kind":"typeIdentifier","preciseIdentifier":"s:SS"}],"kind":"symbol"},"doc://org.cocoapods.PacemakerRadio/documentation/PacemakerRadio/Swift/String/apostrophe":{"type":"topic","kind":"symbol","title":"apostrophe","role":"symbol","identifier":"doc:\/\/org.cocoapods.PacemakerRadio\/documentation\/PacemakerRadio\/Swift\/String\/apostrophe","url":"\/documentation\/pacemakerradio\/swift\/string\/apostrophe","abstract":[],"fragments":[{"text":"var","kind":"keyword"},{"kind":"text","text":" "},{"kind":"identifier","text":"apostrophe"},{"text":": ","kind":"text"},{"kind":"typeIdentifier","preciseIdentifier":"s:SS","text":"String"}]},"doc://org.cocoapods.PacemakerRadio/documentation/PacemakerRadio/Swift/String/c-3cwyk":{"url":"\/documentation\/pacemakerradio\/swift\/string\/c-3cwyk","kind":"symbol","abstract":[],"fragments":[{"text":"var","kind":"keyword"},{"text":" ","kind":"text"},{"text":"c","kind":"identifier"},{"kind":"text","text":": "},{"kind":"typeIdentifier","preciseIdentifier":"s:SS","text":"String"}],"role":"symbol","title":"c","identifier":"doc:\/\/org.cocoapods.PacemakerRadio\/documentation\/PacemakerRadio\/Swift\/String\/c-3cwyk","type":"topic"},"doc://org.cocoapods.PacemakerRadio/documentation/PacemakerRadio/Swift/String/paren_left":{"type":"topic","url":"\/documentation\/pacemakerradio\/swift\/string\/paren_left","abstract":[],"kind":"symbol","title":"paren_left","fragments":[{"text":"var","kind":"keyword"},{"text":" ","kind":"text"},{"kind":"identifier","text":"paren_left"},{"text":": ","kind":"text"},{"kind":"typeIdentifier","preciseIdentifier":"s:SS","text":"String"}],"identifier":"doc:\/\/org.cocoapods.PacemakerRadio\/documentation\/PacemakerRadio\/Swift\/String\/paren_left","role":"symbol"},"doc://org.cocoapods.PacemakerRadio/documentation/PacemakerRadio/Swift/String/semicolon":{"role":"symbol","kind":"symbol","url":"\/documentation\/pacemakerradio\/swift\/string\/semicolon","identifier":"doc:\/\/org.cocoapods.PacemakerRadio\/documentation\/PacemakerRadio\/Swift\/String\/semicolon","title":"semicolon","type":"topic","fragments":[{"kind":"keyword","text":"var"},{"text":" ","kind":"text"},{"kind":"identifier","text":"semicolon"},{"kind":"text","text":": "},{"preciseIdentifier":"s:SS","text":"String","kind":"typeIdentifier"}],"abstract":[]},"doc://org.cocoapods.PacemakerRadio/documentation/PacemakerRadio/Swift/String/G-4gmr8":{"url":"\/documentation\/pacemakerradio\/swift\/string\/g-4gmr8","identifier":"doc:\/\/org.cocoapods.PacemakerRadio\/documentation\/PacemakerRadio\/Swift\/String\/G-4gmr8","fragments":[{"text":"var","kind":"keyword"},{"kind":"text","text":" "},{"text":"G","kind":"identifier"},{"kind":"text","text":": "},{"preciseIdentifier":"s:SS","text":"String","kind":"typeIdentifier"}],"title":"G","type":"topic","role":"symbol","abstract":[],"kind":"symbol"},"doc://org.cocoapods.PacemakerRadio/documentation/PacemakerRadio/Swift/String/colon":{"kind":"symbol","title":"colon","role":"symbol","fragments":[{"text":"var","kind":"keyword"},{"kind":"text","text":" "},{"kind":"identifier","text":"colon"},{"text":": ","kind":"text"},{"kind":"typeIdentifier","text":"String","preciseIdentifier":"s:SS"}],"url":"\/documentation\/pacemakerradio\/swift\/string\/colon","abstract":[],"type":"topic","identifier":"doc:\/\/org.cocoapods.PacemakerRadio\/documentation\/PacemakerRadio\/Swift\/String\/colon"},"doc://org.cocoapods.PacemakerRadio/documentation/PacemakerRadio":{"kind":"symbol","url":"\/documentation\/pacemakerradio","title":"PacemakerRadio","identifier":"doc:\/\/org.cocoapods.PacemakerRadio\/documentation\/PacemakerRadio","role":"collection","abstract":[{"text":"Broadcast your playlist, mix, or set along with your voice, to the world. Tune in to other broadcasts and jump in the conversation with comments, or show your support with quick reactions. An interactive UI for AutomixIQ.","type":"text"}],"type":"topic"},"doc://org.cocoapods.PacemakerRadio/documentation/PacemakerRadio/Swift/String/plus":{"type":"topic","kind":"symbol","title":"plus","role":"symbol","identifier":"doc:\/\/org.cocoapods.PacemakerRadio\/documentation\/PacemakerRadio\/Swift\/String\/plus","url":"\/documentation\/pacemakerradio\/swift\/string\/plus","abstract":[],"fragments":[{"text":"var","kind":"keyword"},{"kind":"text","text":" "},{"kind":"identifier","text":"plus"},{"text":": ","kind":"text"},{"kind":"typeIdentifier","preciseIdentifier":"s:SS","text":"String"}]},"doc://org.cocoapods.PacemakerRadio/documentation/PacemakerRadio/Swift/String/s-9l1x3":{"type":"topic","role":"symbol","fragments":[{"text":"var","kind":"keyword"},{"text":" ","kind":"text"},{"text":"s","kind":"identifier"},{"kind":"text","text":": "},{"preciseIdentifier":"s:SS","kind":"typeIdentifier","text":"String"}],"abstract":[],"url":"\/documentation\/pacemakerradio\/swift\/string\/s-9l1x3","identifier":"doc:\/\/org.cocoapods.PacemakerRadio\/documentation\/PacemakerRadio\/Swift\/String\/s-9l1x3","kind":"symbol","title":"s"},"doc://org.cocoapods.PacemakerRadio/documentation/PacemakerRadio/Swift/String/V-18lpl":{"abstract":[],"fragments":[{"text":"var","kind":"keyword"},{"text":" ","kind":"text"},{"text":"V","kind":"identifier"},{"text":": ","kind":"text"},{"text":"String","kind":"typeIdentifier","preciseIdentifier":"s:SS"}],"identifier":"doc:\/\/org.cocoapods.PacemakerRadio\/documentation\/PacemakerRadio\/Swift\/String\/V-18lpl","type":"topic","role":"symbol","kind":"symbol","url":"\/documentation\/pacemakerradio\/swift\/string\/v-18lpl","title":"V"},"doc://org.cocoapods.PacemakerRadio/documentation/PacemakerRadio/Swift/String/J-2pise":{"role":"symbol","kind":"symbol","url":"\/documentation\/pacemakerradio\/swift\/string\/j-2pise","identifier":"doc:\/\/org.cocoapods.PacemakerRadio\/documentation\/PacemakerRadio\/Swift\/String\/J-2pise","title":"J","type":"topic","fragments":[{"kind":"keyword","text":"var"},{"text":" ","kind":"text"},{"kind":"identifier","text":"J"},{"kind":"text","text":": "},{"preciseIdentifier":"s:SS","text":"String","kind":"typeIdentifier"}],"abstract":[]},"doc://org.cocoapods.PacemakerRadio/documentation/PacemakerRadio/Swift/String/curly_left":{"type":"topic","kind":"symbol","title":"curly_left","role":"symbol","identifier":"doc:\/\/org.cocoapods.PacemakerRadio\/documentation\/PacemakerRadio\/Swift\/String\/curly_left","url":"\/documentation\/pacemakerradio\/swift\/string\/curly_left","abstract":[],"fragments":[{"text":"var","kind":"keyword"},{"kind":"text","text":" "},{"kind":"identifier","text":"curly_left"},{"text":": ","kind":"text"},{"kind":"typeIdentifier","preciseIdentifier":"s:SS","text":"String"}]},"doc://org.cocoapods.PacemakerRadio/documentation/PacemakerRadio/Swift/String/a-6upzr":{"role":"symbol","kind":"symbol","url":"\/documentation\/pacemakerradio\/swift\/string\/a-6upzr","identifier":"doc:\/\/org.cocoapods.PacemakerRadio\/documentation\/PacemakerRadio\/Swift\/String\/a-6upzr","title":"a","type":"topic","fragments":[{"kind":"keyword","text":"var"},{"text":" ","kind":"text"},{"kind":"identifier","text":"a"},{"kind":"text","text":": "},{"preciseIdentifier":"s:SS","text":"String","kind":"typeIdentifier"}],"abstract":[]},"doc://org.cocoapods.PacemakerRadio/documentation/PacemakerRadio/Swift/String/A-5oh0s":{"type":"topic","kind":"symbol","title":"A","role":"symbol","identifier":"doc:\/\/org.cocoapods.PacemakerRadio\/documentation\/PacemakerRadio\/Swift\/String\/A-5oh0s","url":"\/documentation\/pacemakerradio\/swift\/string\/a-5oh0s","abstract":[],"fragments":[{"text":"var","kind":"keyword"},{"kind":"text","text":" "},{"kind":"identifier","text":"A"},{"text":": ","kind":"text"},{"kind":"typeIdentifier","preciseIdentifier":"s:SS","text":"String"}]},"doc://org.cocoapods.PacemakerRadio/documentation/PacemakerRadio/Swift/String/E-6fo8j":{"fragments":[{"kind":"keyword","text":"var"},{"kind":"text","text":" "},{"text":"E","kind":"identifier"},{"kind":"text","text":": "},{"kind":"typeIdentifier","text":"String","preciseIdentifier":"s:SS"}],"identifier":"doc:\/\/org.cocoapods.PacemakerRadio\/documentation\/PacemakerRadio\/Swift\/String\/E-6fo8j","abstract":[],"kind":"symbol","role":"symbol","type":"topic","url":"\/documentation\/pacemakerradio\/swift\/string\/e-6fo8j","title":"E"},"doc://org.cocoapods.PacemakerRadio/documentation/PacemakerRadio/Swift/String/v-3367":{"role":"symbol","kind":"symbol","url":"\/documentation\/pacemakerradio\/swift\/string\/v-3367","identifier":"doc:\/\/org.cocoapods.PacemakerRadio\/documentation\/PacemakerRadio\/Swift\/String\/v-3367","title":"v","type":"topic","fragments":[{"kind":"keyword","text":"var"},{"text":" ","kind":"text"},{"kind":"identifier","text":"v"},{"kind":"text","text":": "},{"preciseIdentifier":"s:SS","text":"String","kind":"typeIdentifier"}],"abstract":[]},"doc://org.cocoapods.PacemakerRadio/documentation/PacemakerRadio/Swift/String/forward_slash":{"type":"topic","kind":"symbol","title":"forward_slash","role":"symbol","identifier":"doc:\/\/org.cocoapods.PacemakerRadio\/documentation\/PacemakerRadio\/Swift\/String\/forward_slash","url":"\/documentation\/pacemakerradio\/swift\/string\/forward_slash","abstract":[],"fragments":[{"text":"var","kind":"keyword"},{"kind":"text","text":" "},{"kind":"identifier","text":"forward_slash"},{"text":": ","kind":"text"},{"kind":"typeIdentifier","preciseIdentifier":"s:SS","text":"String"}]},"doc://org.cocoapods.PacemakerRadio/documentation/PacemakerRadio/Swift/String/caret":{"role":"symbol","abstract":[],"url":"\/documentation\/pacemakerradio\/swift\/string\/caret","title":"caret","fragments":[{"text":"var","kind":"keyword"},{"text":" ","kind":"text"},{"text":"caret","kind":"identifier"},{"text":": ","kind":"text"},{"text":"String","kind":"typeIdentifier","preciseIdentifier":"s:SS"}],"kind":"symbol","type":"topic","identifier":"doc:\/\/org.cocoapods.PacemakerRadio\/documentation\/PacemakerRadio\/Swift\/String\/caret"},"doc://org.cocoapods.PacemakerRadio/documentation/PacemakerRadio/Swift/String/g-6qu19":{"role":"symbol","kind":"symbol","url":"\/documentation\/pacemakerradio\/swift\/string\/g-6qu19","identifier":"doc:\/\/org.cocoapods.PacemakerRadio\/documentation\/PacemakerRadio\/Swift\/String\/g-6qu19","title":"g","type":"topic","fragments":[{"kind":"keyword","text":"var"},{"text":" ","kind":"text"},{"kind":"identifier","text":"g"},{"text":": ","kind":"text"},{"preciseIdentifier":"s:SS","text":"String","kind":"typeIdentifier"}],"abstract":[]},"doc://org.cocoapods.PacemakerRadio/documentation/PacemakerRadio/Swift/String/ampersand":{"abstract":[],"url":"\/documentation\/pacemakerradio\/swift\/string\/ampersand","role":"symbol","identifier":"doc:\/\/org.cocoapods.PacemakerRadio\/documentation\/PacemakerRadio\/Swift\/String\/ampersand","kind":"symbol","title":"ampersand","type":"topic","fragments":[{"kind":"keyword","text":"var"},{"text":" ","kind":"text"},{"kind":"identifier","text":"ampersand"},{"kind":"text","text":": "},{"kind":"typeIdentifier","text":"String","preciseIdentifier":"s:SS"}]},"doc://org.cocoapods.PacemakerRadio/documentation/PacemakerRadio/Swift/String/comma":{"identifier":"doc:\/\/org.cocoapods.PacemakerRadio\/documentation\/PacemakerRadio\/Swift\/String\/comma","abstract":[],"role":"symbol","fragments":[{"text":"var","kind":"keyword"},{"text":" ","kind":"text"},{"kind":"identifier","text":"comma"},{"kind":"text","text":": "},{"kind":"typeIdentifier","text":"String","preciseIdentifier":"s:SS"}],"url":"\/documentation\/pacemakerradio\/swift\/string\/comma","title":"comma","type":"topic","kind":"symbol"},"doc://org.cocoapods.PacemakerRadio/documentation/PacemakerRadio/Swift/String/L-4rbao":{"title":"L","url":"\/documentation\/pacemakerradio\/swift\/string\/l-4rbao","identifier":"doc:\/\/org.cocoapods.PacemakerRadio\/documentation\/PacemakerRadio\/Swift\/String\/L-4rbao","role":"symbol","type":"topic","abstract":[],"fragments":[{"kind":"keyword","text":"var"},{"text":" ","kind":"text"},{"kind":"identifier","text":"L"},{"kind":"text","text":": "},{"preciseIdentifier":"s:SS","kind":"typeIdentifier","text":"String"}],"kind":"symbol"},"doc://org.cocoapods.PacemakerRadio/documentation/PacemakerRadio/Swift/String/bar":{"title":"bar","identifier":"doc:\/\/org.cocoapods.PacemakerRadio\/documentation\/PacemakerRadio\/Swift\/String\/bar","kind":"symbol","abstract":[],"url":"\/documentation\/pacemakerradio\/swift\/string\/bar","role":"symbol","type":"topic","fragments":[{"text":"var","kind":"keyword"},{"kind":"text","text":" "},{"kind":"identifier","text":"bar"},{"text":": ","kind":"text"},{"preciseIdentifier":"s:SS","text":"String","kind":"typeIdentifier"}]},"doc://org.cocoapods.PacemakerRadio/documentation/PacemakerRadio/Swift/String/X-4xctw":{"type":"topic","url":"\/documentation\/pacemakerradio\/swift\/string\/x-4xctw","kind":"symbol","title":"X","abstract":[],"fragments":[{"text":"var","kind":"keyword"},{"text":" ","kind":"text"},{"kind":"identifier","text":"X"},{"text":": ","kind":"text"},{"preciseIdentifier":"s:SS","text":"String","kind":"typeIdentifier"}],"identifier":"doc:\/\/org.cocoapods.PacemakerRadio\/documentation\/PacemakerRadio\/Swift\/String\/X-4xctw","role":"symbol"},"doc://org.cocoapods.PacemakerRadio/documentation/PacemakerRadio/Swift/String/dash":{"title":"dash","url":"\/documentation\/pacemakerradio\/swift\/string\/dash","abstract":[],"role":"symbol","fragments":[{"kind":"keyword","text":"var"},{"text":" ","kind":"text"},{"text":"dash","kind":"identifier"},{"text":": ","kind":"text"},{"kind":"typeIdentifier","preciseIdentifier":"s:SS","text":"String"}],"type":"topic","kind":"symbol","identifier":"doc:\/\/org.cocoapods.PacemakerRadio\/documentation\/PacemakerRadio\/Swift\/String\/dash"},"doc://org.cocoapods.PacemakerRadio/documentation/PacemakerRadio/Swift/String/H-6ow9j":{"url":"\/documentation\/pacemakerradio\/swift\/string\/h-6ow9j","identifier":"doc:\/\/org.cocoapods.PacemakerRadio\/documentation\/PacemakerRadio\/Swift\/String\/H-6ow9j","fragments":[{"text":"var","kind":"keyword"},{"text":" ","kind":"text"},{"text":"H","kind":"identifier"},{"text":": ","kind":"text"},{"kind":"typeIdentifier","preciseIdentifier":"s:SS","text":"String"}],"title":"H","type":"topic","role":"symbol","abstract":[],"kind":"symbol"},"doc://org.cocoapods.PacemakerRadio/documentation/PacemakerRadio/Swift/String/I-9vxw8":{"type":"topic","fragments":[{"kind":"keyword","text":"var"},{"text":" ","kind":"text"},{"kind":"identifier","text":"I"},{"kind":"text","text":": "},{"kind":"typeIdentifier","text":"String","preciseIdentifier":"s:SS"}],"kind":"symbol","title":"I","role":"symbol","identifier":"doc:\/\/org.cocoapods.PacemakerRadio\/documentation\/PacemakerRadio\/Swift\/String\/I-9vxw8","abstract":[],"url":"\/documentation\/pacemakerradio\/swift\/string\/i-9vxw8"},"doc://org.cocoapods.PacemakerRadio/documentation/PacemakerRadio/Swift/String/dot":{"title":"dot","url":"\/documentation\/pacemakerradio\/swift\/string\/dot","identifier":"doc:\/\/org.cocoapods.PacemakerRadio\/documentation\/PacemakerRadio\/Swift\/String\/dot","role":"symbol","type":"topic","abstract":[],"fragments":[{"kind":"keyword","text":"var"},{"text":" ","kind":"text"},{"kind":"identifier","text":"dot"},{"kind":"text","text":": "},{"kind":"typeIdentifier","text":"String","preciseIdentifier":"s:SS"}],"kind":"symbol"},"doc://org.cocoapods.PacemakerRadio/documentation/PacemakerRadio/Swift/String/bracket_right":{"type":"topic","kind":"symbol","title":"bracket_right","role":"symbol","identifier":"doc:\/\/org.cocoapods.PacemakerRadio\/documentation\/PacemakerRadio\/Swift\/String\/bracket_right","abstract":[],"url":"\/documentation\/pacemakerradio\/swift\/string\/bracket_right","fragments":[{"text":"var","kind":"keyword"},{"text":" ","kind":"text"},{"kind":"identifier","text":"bracket_right"},{"text":": ","kind":"text"},{"kind":"typeIdentifier","text":"String","preciseIdentifier":"s:SS"}]},"doc://org.cocoapods.PacemakerRadio/documentation/PacemakerRadio/Swift/String/W-9er54":{"fragments":[{"kind":"keyword","text":"var"},{"text":" ","kind":"text"},{"kind":"identifier","text":"W"},{"kind":"text","text":": "},{"kind":"typeIdentifier","preciseIdentifier":"s:SS","text":"String"}],"url":"\/documentation\/pacemakerradio\/swift\/string\/w-9er54","type":"topic","abstract":[],"identifier":"doc:\/\/org.cocoapods.PacemakerRadio\/documentation\/PacemakerRadio\/Swift\/String\/W-9er54","title":"W","role":"symbol","kind":"symbol"},"doc://org.cocoapods.PacemakerRadio/documentation/PacemakerRadio/Swift/String/asterisk":{"role":"symbol","fragments":[{"kind":"keyword","text":"var"},{"text":" ","kind":"text"},{"text":"asterisk","kind":"identifier"},{"kind":"text","text":": "},{"text":"String","kind":"typeIdentifier","preciseIdentifier":"s:SS"}],"url":"\/documentation\/pacemakerradio\/swift\/string\/asterisk","abstract":[],"type":"topic","title":"asterisk","kind":"symbol","identifier":"doc:\/\/org.cocoapods.PacemakerRadio\/documentation\/PacemakerRadio\/Swift\/String\/asterisk"},"doc://org.cocoapods.PacemakerRadio/documentation/PacemakerRadio/Swift/String/at":{"type":"topic","fragments":[{"kind":"keyword","text":"var"},{"kind":"text","text":" "},{"text":"at","kind":"identifier"},{"kind":"text","text":": "},{"kind":"typeIdentifier","preciseIdentifier":"s:SS","text":"String"}],"kind":"symbol","title":"at","role":"symbol","identifier":"doc:\/\/org.cocoapods.PacemakerRadio\/documentation\/PacemakerRadio\/Swift\/String\/at","abstract":[],"url":"\/documentation\/pacemakerradio\/swift\/string\/at"},"doc://org.cocoapods.PacemakerRadio/documentation/PacemakerRadio/Swift/String/j-3xz8n":{"title":"j","url":"\/documentation\/pacemakerradio\/swift\/string\/j-3xz8n","identifier":"doc:\/\/org.cocoapods.PacemakerRadio\/documentation\/PacemakerRadio\/Swift\/String\/j-3xz8n","role":"symbol","type":"topic","abstract":[],"fragments":[{"kind":"keyword","text":"var"},{"kind":"text","text":" "},{"text":"j","kind":"identifier"},{"kind":"text","text":": "},{"preciseIdentifier":"s:SS","kind":"typeIdentifier","text":"String"}],"kind":"symbol"},"doc://org.cocoapods.PacemakerRadio/documentation/PacemakerRadio/Swift/String/space":{"type":"topic","fragments":[{"kind":"keyword","text":"var"},{"text":" ","kind":"text"},{"kind":"identifier","text":"space"},{"kind":"text","text":": "},{"kind":"typeIdentifier","text":"String","preciseIdentifier":"s:SS"}],"kind":"symbol","title":"space","role":"symbol","identifier":"doc:\/\/org.cocoapods.PacemakerRadio\/documentation\/PacemakerRadio\/Swift\/String\/space","abstract":[],"url":"\/documentation\/pacemakerradio\/swift\/string\/space"}}}